[
   {
    "name": "Sanzida Alam",
    "university": "University of Chittagong",
    "department": "English",
    "admissionYear": 2019,
    "sscBatch": 2016,
    "photo": "images/sanzida.jpeg"
  },
   {
    "name": "Md Yasin Arafat",
    "university": "Comilla University",
    "department": "Pharmacy",
    "admissionYear": 2023,
    "sscBatch": 2020,
    "photo": "images/yasin.jpg"
  },
  {
    "name": "Sanjid Alam",
    "university": "Rajshahi University of Engineering & Technology",
    "department": "Computer Science and Engineering",
    "admissionYear": 2025,
    "sscBatch": 2022,
    "photo": "images/sanjid.jpg"
  },
   {
    "name": "Shihab Uddin",
    "university": "Daffodil International University",
    "department": "Computer Science and Engineering",
    "admissionYear": 2025,
    "sscBatch": 2022,
    "photo": "images/shihab.jpg"
  },
   {
    "name": "Jannatul Mawya",
    "university": "Comilla University",
    "department": "Finance",
    "admissionYear": 2026,
    "sscBatch": 2023,
    "photo": "images/mawya.jpg"
  },
   {
    "name": "Nazrul Islam Nafis",
    "university": "University of Dhaka",
    "department": "Economics",
    "admissionYear": 2026,
    "sscBatch": 2023,
    "photo": "images/nafis.jpg"
  }
]
